NumAn_Op/__init__.py
NumAn_Op/multi_dim_min.py
NumAn_Op/one_dim_min.py
NumAn_Op/sys_eq.py
NumAn_Op-0.0.2.dist-info/LICENSE
NumAn_Op-0.0.2.dist-info/METADATA
NumAn_Op-0.0.2.dist-info/WHEEL
NumAn_Op-0.0.2.dist-info/top_level.txt
NumAn_Op-0.0.2.dist-info/RECORD
