Metadata-Version: 2.1
Name: NumAn-Op
Version: 0.0.2
Summary: NumAn_Op (stands for Numerical Analysis & Optimization) is a python package that contains some optimization algorithms.
Home-page: https://github.com/FILALIHicham/Numerical_Analysis_Optimization_Package
Author: Hicham FILALI
Author-email: hicham.filali@ieee.org
License: UNKNOWN
Platform: UNKNOWN
Classifier: Programming Language :: Python :: 3
Classifier: License :: OSI Approved :: MIT License
Classifier: Operating System :: OS Independent
Requires-Python: >=3.5
License-File: LICENSE
